Metadata-Version: 2.1
Name: sqlLinter
Version: 0.0.23
Summary: Linter tool for SQL packages written in Python
Home-page: https://github.com/walshdanny700/sqlLinter
Author: Danny Walsh
Author-email: walshdanny700@gmail.com
License: UNKNOWN
Platform: UNKNOWN
Classifier: Programming Language :: Python
Classifier: Programming Language :: Python :: 3.6
Classifier: Programming Language :: Python :: 3.7
Classifier: License :: OSI Approved :: MIT License
Classifier: Operating System :: OS Independent
